README.txt
setup.py
zerobugz/__init__.py
zerobugz/core.py
zerobugz.egg-info/PKG-INFO
zerobugz.egg-info/SOURCES.txt
zerobugz.egg-info/dependency_links.txt
zerobugz.egg-info/requires.txt
zerobugz.egg-info/top_level.txt